Metadata-Version: 1.1
Name: metabolace
Version: 1.3.0
Summary: Active fork of lace, the Body Labs-developed polygonal mesh library
Home-page: https://github.com/metabolize/lace
Author: Body Labs
Author-email: alex@bodylabs.com
License: MIT
Platform: UNKNOWN
Classifier: Development Status :: 3 - Alpha
Classifier: Intended Audience :: Developers
Classifier: License :: OSI Approved :: BSD License
Classifier: Operating System :: OS Independent
Classifier: Programming Language :: Python :: 2.7
